README.rst
setup.py
nanogen/__init__.py
nanogen/cli.py
nanogen/logger.py
nanogen/models.py
nanogen/renderer.py
nanogen/utils.py
nanogen/version.py
nanogen.egg-info/PKG-INFO
nanogen.egg-info/SOURCES.txt
nanogen.egg-info/dependency_links.txt
nanogen.egg-info/entry_points.txt
nanogen.egg-info/requires.txt
nanogen.egg-info/top_level.txt