Metadata-Version: 1.1
Name: nanogen
Version: 2.1.2
Summary: A very small static blog generator
Home-page: https://github.com/epochblue/nanogen
Author: Bill Israel
Author-email: bill.israel@gmail.com
License: MIT
Keywords: command line,static generator,blog
Platform: UNKNOWN
Classifier: Development Status :: 4 - Beta
Classifier: Environment :: Console
Classifier: Intended Audience :: Developers
Classifier: Intended Audience :: Information Technology
Classifier: License :: OSI Approved :: MIT License
Classifier: Operating System :: OS Independent
Classifier: Programming Language :: Python :: 3.3
Classifier: Programming Language :: Python :: 3.4
Classifier: Programming Language :: Python :: 3.5
Classifier: Programming Language :: Python :: 3.6
Classifier: Topic :: Internet :: WWW/HTTP
Classifier: Topic :: Utilities
Classifier: Topic :: Software Development :: Libraries :: Python Modules
